dynamic_topic_modeling/__init__.py
dynamic_topic_modeling/_nbdev.py
dynamic_topic_modeling/dtm.py
dynamic_topic_modeling/gensim_lda.py
dynamic_topic_modeling/sklearn_lda.py
dynamic_topic_modeling-1.1.0.dist-info/LICENSE.md
dynamic_topic_modeling-1.1.0.dist-info/METADATA
dynamic_topic_modeling-1.1.0.dist-info/WHEEL
dynamic_topic_modeling-1.1.0.dist-info/entry_points.txt
dynamic_topic_modeling-1.1.0.dist-info/top_level.txt
dynamic_topic_modeling-1.1.0.dist-info/RECORD
